primarycolors/__init__.py
primarycolors-0.6.3.data/scripts/pcolor
primarycolors-0.6.3.dist-info/DESCRIPTION.rst
primarycolors-0.6.3.dist-info/METADATA
primarycolors-0.6.3.dist-info/metadata.json
primarycolors-0.6.3.dist-info/RECORD
primarycolors-0.6.3.dist-info/top_level.txt
primarycolors-0.6.3.dist-info/WHEEL
