Metadata-Version: 2.0
Name: primarycolors
Version: 0.6.3
Summary: Determination of the primary colors in an image file.
Home-page: https://bitbucket.org/rodion_s/primarycolors
Author: Rodion S.
Author-email: python@profserver.ru
License: GPL
Keywords: clustering,colors,primary colors,k-means
Platform: Linux
Platform: MacOS X
Classifier: Development Status :: 4 - Beta
Classifier: Topic :: Utilities
Classifier: Environment :: Console
Classifier: License :: OSI Approved :: GNU General Public License (GPL)
Classifier: Operating System :: OS Independent
Classifier: Topic :: Scientific/Engineering :: Artificial Intelligence
Classifier: Topic :: Software Development :: Libraries :: Python Modules
Classifier: Topic :: Internet :: WWW/HTTP
Classifier: Programming Language :: Python
Classifier: Programming Language :: Python :: 2.7
Classifier: Programming Language :: Python :: 3.4
Requires: six
Requires: numpy
Requires: Pillow
Requires: scipy
